setup.cfg
setup.py
src/GenotypeNetwork.py
src/__init__.py
src/binary_to_network.py
src/cosi_to_binary.py
src/custom_exceptions.py
src/filteredvcf_to_binary.py
src/generate_network_report.py
src/get_gene_coords.py
src/get_genotypes_from_1000Genomes.py
src/get_simulations_background.py
src/vcf2networks.py
test/test_AveragePathLenghtCalculation.py
test/test_BinaryToNetwork.py
test/test_CosiToBinary.py
test/test_GenotypeNetwork.py
test/test_GenotypeNetworkDistance.py
test/test_GenotypeNetworkIndividuals.py
test/test_GetGenotypes.py
test/test_ReadFromGraphml.py
test/test_Report.py
test/test_ReportAdvancedFeatures.py
test/test_ReportByNode.py
test/test_ReportWindows.py
test/test_SimulationsBackground.py
test/test_SubgraphByPop.py
test/test_SubgraphByPopFromFile.py
test/test_ValuesByNodeReport.py
test/test_Vcf2Binary.py
test/test_Vcf2Networks_call.py
test/test_commandline_options.py
vcf2networks.egg-info/PKG-INFO
vcf2networks.egg-info/SOURCES.txt
vcf2networks.egg-info/dependency_links.txt
vcf2networks.egg-info/entry_points.txt
vcf2networks.egg-info/requires.txt
vcf2networks.egg-info/top_level.txt