Metadata-Version: 1.1
Name: vcf2networks
Version: 1.0.9f
Summary: calculate Genotype Networks from VCF files
Home-page: https://bitbucket.org/dalloliogm/vcf2networks
Author: Giovanni M. Dall'Olio
Author-email: giovanni.dallolio@upf.edu
License: GPL
Download-URL: https://bitbucket.org/dalloliogm/vcf2networks/get/tip.zip
Keywords: genetics,variant,nucleotide variant,vcf,population genetics,bioinformatics,networks,genotype networks
Platform: UNKNOWN
Classifier: License :: OSI Approved :: GNU General Public License (GPL)
Classifier: Programming Language :: Python
Classifier: Development Status :: 4 - Beta
Classifier: Intended Audience :: Science/Research
Classifier: Topic :: Scientific/Engineering :: Bio-Informatics
